{
  "timestamp" : "2024-07-30T00:33:52Z",
  "count_outdated" : 1251,
  "uniques_outdated" : 345,
  "count" : 1257,
  "uniques" : 348,
  "views" : [
    {
      "timestamp": "2024-07-18T00:00:00Z",
      "count": 2,
      "count_minmax": [ 2, 2 ],
      "count_decinc": [ 0, 2 ],
      "uniques": 1,
      "uniques_minmax": [ 1, 1 ],
      "uniques_decinc": [ 0, 1 ]
    },
    {
      "timestamp": "2024-07-19T00:00:00Z",
      "count": 2,
      "count_minmax": [ 2, 2 ],
      "count_decinc": [ 0, 2 ],
      "uniques": 1,
      "uniques_minmax": [ 1, 1 ],
      "uniques_decinc": [ 0, 1 ]
    },
    {
      "timestamp": "2024-07-29T00:00:00Z",
      "count": 2,
      "count_minmax": [ 2, 2 ],
      "count_decinc": [ 0, 2 ],
      "uniques": 1,
      "uniques_minmax": [ 1, 1 ],
      "uniques_decinc": [ 0, 1 ]
    }
  ]
}
