{
  "timestamp" : "2024-09-25T01:14:23Z",
  "count_outdated" : 1316,
  "uniques_outdated" : 365,
  "count" : 1334,
  "uniques" : 371,
  "views" : [
    {
      "timestamp": "2024-09-11T00:00:00Z",
      "count": 4,
      "count_minmax": [ 4, 4 ],
      "count_decinc": [ 0, 4 ],
      "uniques": 1,
      "uniques_minmax": [ 1, 1 ],
      "uniques_decinc": [ 0, 1 ]
    },
    {
      "timestamp": "2024-09-12T00:00:00Z",
      "count": 2,
      "count_minmax": [ 2, 2 ],
      "count_decinc": [ 0, 2 ],
      "uniques": 1,
      "uniques_minmax": [ 1, 1 ],
      "uniques_decinc": [ 0, 1 ]
    },
    {
      "timestamp": "2024-09-13T00:00:00Z",
      "count": 2,
      "count_minmax": [ 2, 2 ],
      "count_decinc": [ 0, 2 ],
      "uniques": 1,
      "uniques_minmax": [ 1, 1 ],
      "uniques_decinc": [ 0, 1 ]
    },
    {
      "timestamp": "2024-09-14T00:00:00Z",
      "count": 2,
      "count_minmax": [ 2, 2 ],
      "count_decinc": [ 0, 2 ],
      "uniques": 1,
      "uniques_minmax": [ 1, 1 ],
      "uniques_decinc": [ 0, 1 ]
    },
    {
      "timestamp": "2024-09-19T00:00:00Z",
      "count": 4,
      "count_minmax": [ 4, 4 ],
      "count_decinc": [ 0, 4 ],
      "uniques": 1,
      "uniques_minmax": [ 1, 1 ],
      "uniques_decinc": [ 0, 1 ]
    },
    {
      "timestamp": "2024-09-24T00:00:00Z",
      "count": 4,
      "count_minmax": [ 4, 4 ],
      "count_decinc": [ 0, 4 ],
      "uniques": 1,
      "uniques_minmax": [ 1, 1 ],
      "uniques_decinc": [ 0, 1 ]
    }
  ]
}
